[
  { "ambient_light": { "color": [1.0, 1.0, 1.0] } },
  {
    "camera": {
      "position": [5.0, 0.0, 0.0],
      "viewdir": [-1.0, 0.0, 0.0],
      "updir": [0.0, 1.0, 0.0]
    }
  },
  {
    "rotate": [
      [1.0, 0.0, 0.0],
      1.6,
      [
        {
          "rotate": [
            [0.0, 1.0, 0.0],
            -0.5,
            [
              {
                "cylinder": {
                  "material": { "ambient": { "constant": [0.5, 0.0, 0.0] } }
                }
              }
            ]
          ]
        }
      ]
    ]
  }
]
